mordl/__init__.py
mordl/_version.py
mordl/base_model.py
mordl/base_tagger.py
mordl/base_tagger_model.py
mordl/base_tagger_sequence_model.py
mordl/defaults.py
mordl/deprel_tagger.py
mordl/deprel_tagger_model.py
mordl/feat_tagger.py
mordl/feat_tagger_model.py
mordl/feats_binary_tagger.py
mordl/feats_binary_tagger_model.py
mordl/feats_tagger.py
mordl/lemma_tagger.py
mordl/ne_tagger.py
mordl/syntax_tagger_model.py
mordl/upos_tagger.py
mordl/upos_tagger_model.py
mordl/word_embeddings.py
mordl/lib/__init__.py
mordl/lib/conll18_ud_eval.py
mordl-2.0.12.dist-info/LICENSE
mordl-2.0.12.dist-info/METADATA
mordl-2.0.12.dist-info/WHEEL
mordl-2.0.12.dist-info/top_level.txt
mordl-2.0.12.dist-info/RECORD
