Metadata-Version: 2.1
Name: mordl
Version: 2.0.12
Summary: Morphological parser (POS, lemmata, NER etc.)
Home-page: https://github.com/fostroll/mordl
Author: Sergei Ternovykh, Anastasiya Nikiforova
Author-email: fostroll@gmail.com, steysie@gmail.com
License: BSD
Keywords: natural-language-processing nlp morphology
Platform: UNKNOWN
Classifier: Development Status :: 3 - Alpha
Classifier: Intended Audience :: Developers
Classifier: Intended Audience :: Education
Classifier: Intended Audience :: Science/Research
Classifier: Intended Audience :: Information Technology
Classifier: Topic :: Scientific/Engineering
Classifier: Topic :: Scientific/Engineering :: Artificial Intelligence
Classifier: Topic :: Scientific/Engineering :: Information Analysis
Classifier: Topic :: Text Processing
Classifier: Topic :: Text Processing :: Linguistic
Classifier: Topic :: Software Development
Classifier: Topic :: Software Development :: Libraries
Classifier: Programming Language :: Python :: 3.6
Classifier: Programming Language :: Python :: 3.7
Classifier: Programming Language :: Python :: 3.8
Classifier: Programming Language :: Python :: 3.9
Classifier: Programming Language :: Python :: 3.10
Requires-Python: >=3.6
Requires-Dist: corpuscula (>=1.0.56)
Requires-Dist: gensim (>=3.8.3)
Requires-Dist: junky (>=1.1.5)
Requires-Dist: morra (>=1.0.7)
Requires-Dist: numpy
Requires-Dist: python-Levenshtein
Requires-Dist: sklearn
Requires-Dist: torch (>=1.8.0)
Requires-Dist: transformers (>=4.3.3)
